setup.py
gym_pull/__init__.py
gym_pull/version.py
gym_pull.egg-info/PKG-INFO
gym_pull.egg-info/SOURCES.txt
gym_pull.egg-info/dependency_links.txt
gym_pull.egg-info/not-zip-safe
gym_pull.egg-info/requires.txt
gym_pull.egg-info/top_level.txt
gym_pull/envs/__init__.py
gym_pull/envs/registration.py
gym_pull/monitoring/__init__.py
gym_pull/monitoring/monitor.py
gym_pull/package/__init__.py
gym_pull/package/manager.py
gym_pull/scoreboard/__init__.py
gym_pull/scoreboard/api.py