Metadata-Version: 1.0
Name: gym-pull
Version: 0.1.6
Summary: Add-on for OpenAI Gym that supports automatic downloading of user environments.
Home-page: https://github.com/ppaquette/gym-pull
Author: Philip Paquette
Author-email: pcpaquette@gmail.com
License: MIT License
Platform: UNKNOWN
